setup.py
makobot/__init__.py
makobot/__main__.py
makobot/slackbot_settings.py
makobot/utils.py
makobot.egg-info/PKG-INFO
makobot.egg-info/SOURCES.txt
makobot.egg-info/dependency_links.txt
makobot.egg-info/requires.txt
makobot.egg-info/top_level.txt
makobot/bots/__init__.py
makobot/bots/email.py
makobot/bots/help.py
makobot/bots/host.py
makobot/bots/ip.py
makobot/bots/md5.py
makobot/bots/url.py
makobot/libs/__init__.py
makobot/libs/virustotal.py
makobot/libs/xforce.py
makobot/plugins/__init__.py
makobot/plugins/base.py
makobot/plugins/extractor.py
makobot/plugins/manager.py
makobot/plugins/threatconnect.py
makobot/plugins/virustotal.py
makobot/plugins/xforce.py
tests/__init__.py
tests/libs/__init__.py
tests/libs/test_virustotal.py
tests/libs/test_xforce.py
tests/plugins/__init__.py
tests/plugins/test_base.py
tests/plugins/test_extractor.py
tests/plugins/test_manager.py
tests/plugins/test_threatconnect.py
tests/plugins/test_virustotal.py
tests/plugins/test_xforce.py